{
  "schema": "bsv-app",
  "schemaVersion": "1.0",
  "topicManagers": {},
  "lookupServices": {},
  "frontend": {
    "language": "react",
    "sourceDirectory": "./frontend"
  },
  "contracts": {},
  "configs": [
    {
      "name": "Local LARS",
      "network": "mainnet",
      "provider": "LARS",
      "run": [
        "frontend"
      ]
    },
    {
      "name": "helloworld_overlay",
      "provider": "CARS",
      "CARSCloudURL": "https://cars.babbage.systems",
      "projectID": "2e97d492e90354a3a453e526cf53819c",
      "network": "mainnet",
      "deploy": [
        "frontend"
      ],
      "frontendHostingMethod": "HTTPS"
    }
  ]
}
